<?xml version="1.0" encoding="utf-8"?>
<ModelInfo>

	<LODS>
		<LOD minSize="25" ModelFile="HTAI Cessna 206 Stationair Early WP MSFS_LOD0.gltf"/>
		<LOD minSize="20" ModelFile="HTAI Cessna 206 Stationair Early WP MSFS_LOD1.gltf"/>
		<LOD minSize="15" ModelFile="HTAI Cessna 206 Stationair Early WP MSFS_LOD2.gltf"/>
		<LOD minSize="10" ModelFile="HTAI Cessna 206 Stationair Early WP MSFS_LOD3.gltf"/>
		<LOD minSize="3" ModelFile="HTAI Cessna 206 Stationair Early WP MSFS_LOD4.gltf"/>
		<LOD minSize="0.5" ModelFile="HTAI Cessna 206 Stationair Early WP MSFS_LOD5.gltf"/>
	</LODS>

	<Behaviors>
		<IncludeBase ModelBehaviorFile="AIG\AircraftBases\HTAI_Cessna_SE.xml"/>

		<Component ID="HTAI_Cessna_SE_Templates">
			<UseTemplate Name="HTAI_Cessna_206_Flaps"/>
			<UseTemplate Name="HTAI_Cessna_GroundParts"/>
		</Component>

	</Behaviors>

</ModelInfo>